antenna_simulation_driver/__init__.py
antenna_simulation_driver/necpp_output_parser.py
antenna_simulation_driver-0.1.3.dist-info/LICENSE
antenna_simulation_driver-0.1.3.dist-info/METADATA
antenna_simulation_driver-0.1.3.dist-info/NOTICE
antenna_simulation_driver-0.1.3.dist-info/WHEEL
antenna_simulation_driver-0.1.3.dist-info/top_level.txt
antenna_simulation_driver-0.1.3.dist-info/RECORD
