Metadata-Version: 2.2
Name: antenna_simulation_driver
Version: 0.1.3
Summary: Software to run antenna simulations, for parameter studies and optimizations.
Author-email: "Dr. Andreas Krüger, DJ3EI" <dj3ei@famsik.de>
Project-URL: Homepage, https://gitlab.com/4ham/antenna_simulation_driver
Project-URL: Repository, https://gitlab.com/4ham/antenna_simulation_driver
Project-URL: Issues, https://gitlab.com/4ham/antenna_simulation_driver/-/issues
Keywords: ham,amateur radio
Classifier: Programming Language :: Python :: 3
Classifier: License :: OSI Approved :: MIT License
Classifier: Operating System :: OS Independent
Classifier: Development Status :: 3 - Alpha
Classifier: Intended Audience :: Developers
Classifier: Intended Audience :: Education
Classifier: Topic :: Communications :: Ham Radio
Requires-Python: >=3.11
License-File: LICENSE
License-File: NOTICE
Requires-Dist: numpy>=2.1.3
